{
  "AGIMUS Reigns!": {
    "file": "data/clips/agimusreigns.mp4",
    "description": "AGIMUS reigns with this ship's materials I will produce a whole fleet of murder drones this planet nay this system will be mine you fool you trusted me",
    "url": "https://i.imgur.com/uiacPCt.mp4"
  },
  "AGIMUS YESSS!": {
    "file": "data/clips/agimusyes.mp4",
    "description": "AGIMUS yes",
    "url": "https://i.imgur.com/KxfDkTT.mp4"
  },
  "ALLAMARAINE!!!": {
    "file": "data/clips/allamaraine.mp4",
    "description": "Move Along Home. DS9. Deep Space Nine.",
    "url": "https://i.imgur.com/lnk9ZCv.mp4"
  },
  "Beverly! Have Trust In Me!": {
    "file": "data/clips/beverleyhavetrustinme.mp4",
    "description": "Sub Rosa Beverly",
    "url": "https://i.imgur.com/brGRkOz.mp4"
  },
  "Blooper - Michael Dorn/Worf - God, JESUS!": {
    "file": "data/clips/blooperworfgodjesus.mp4",
    "description": "Blooper Michael Dorn Worf God JESUS",
    "url": "https://i.imgur.com/YS5gQtL.mp4"
  },
  "Blooper - Michael Dorn/Worf - Aw shit..": {
    "file": "data/clips/blooperworfawshit.mp4",
    "description": "Blooper Michael Dorn Worf oh aw shit",
    "url": "https://i.imgur.com/aaUzAyk.mp4"
  },
  "Blooper - Whoopi Goldberg/Guinan - Ferengi Fucker": {
    "file": "data/clips/blooperguinanferengifucker.mp4",
    "description": "You think that Ferengi fucker killed himself",
    "url": "https://i.imgur.com/MTNIhNO.mp4"
  },
  "Boimler - RIKER!": {
    "file": "data/clips/boimlerriker.mp4",
    "description": "Boimler Riker Lower Decks Strange New Worlds",
    "url": "https://i.imgur.com/n04mMMQ.mp4"
  },
  "Darmok And Jalad At Tanagra": {
    "file": "data/clips/darmokandjaladattanagra.mp4",
    "description": "Tamarian Language Darmok And Jalad At Tanagra",
    "url": "https://i.imgur.com/fIuRXPW.mp4"
  },
  "Data - It Is Green!": {
    "file": "data/clips/dataitisgreen.mp4",
    "description": "Data it is green",
    "url": "https://i.imgur.com/d1bZLNC.mp4"
  },
  "Data - It Is Revolting!": {
    "file": "data/clips/dataitisrevolting.mp4",
    "description": "Data it is its revolting",
    "url": "https://i.imgur.com/I9mvDej.mp4"
  },
  "Data - Lifeforms Song": {
    "file": "data/clips/datalifeforms.mp4",
    "description": "Generations Data Lifeforms Life Forms Song",
    "url": "https://i.imgur.com/J4ApFAf.mp4"
  },
  "Data - Petty Bickering": {
    "file": "data/clips/datapettybickering.mp4",
    "description": "Data could you please continue the petty bickering I find it most intriguing",
    "url": "https://i.imgur.com/ep7lGpE.mp4"
  },
  "Data - Oh Shit!": {
    "file": "data/clips/dataohshit.mp4",
    "description": "Data Ohhhh Shit",
    "url": "https://i.imgur.com/GH7Dy2J.mp4"
  },
  "Data - Yesss!": {
    "file": "data/clips/datayesss.mp4",
    "description": "Data Yes",
    "url": "https://i.imgur.com/nHAdPH2.mp4"
  },
  "Did I Win!? HARDLY!": {
    "file": "data/clips/didiwinhardly.mp4",
    "description": "Quark You're required to learn as you play, roll. Move Along Home",
    "url": "https://i.imgur.com/TPMEP6c.mp4"
  },
  "Coffee, Black. MAKE IT YOURSELF!": {
    "file": "data/clips/coffeeblackmakeityourself.mp4",
    "description": "Janeway Computer Majel Barrett",
    "url": "https://i.imgur.com/Jj97Mqc.mp4"
  },
  "Come! ENTER FRIEND!": {
    "file": "data/clips/comeenterfriend.mp4",
    "description": "Mariner Boimler Tendi Come Come Enter Friend Lower Decks",
    "url": "https://i.imgur.com/yhaiV4H.mp4"
  },
  "Fire All The Torpedos!": {
    "file": "data/clips/fireallthetorpedos.mp4",
    "description": "Fire All The Torpedos",
    "url": "https://i.imgur.com/5tCFxQZ.mp4"
  },
  "Garak - Especially The Lies": {
    "file": "data/clips/garakespeciallythelies.mp4",
    "description": "My dear doctor they're all true, even the lies, especially the lies",
    "url": "https://i.imgur.com/KayZHFN.mp4"
  },
  "Geordi - Leak? I'm not detecting any leak?": {
    "file": "data/clips/geordinotdetectinganyleak.mp4",
    "description": "Geordi leak I'm not detecting any leak",
    "url": "https://i.imgur.com/MngSWdu.mp4"
  },
  "Icheb's Brother - How Are You?": {
    "file": "data/clips/ichebsbrotherhowareyou.mp4",
    "description": "Sewage Voyager",
    "url": "https://i.imgur.com/lDbD4oG.mp4"
  },
  "Shax - IT'S NAKED TIME!!!": {
    "file": "data/clips/itsnakedtime.mp4",
    "description": "Its Naked Time. Lower Decks.",
    "url": "https://i.imgur.com/RrJGU9G.mp4"
  },
  "Keiko's Gonna Have A Baby! ... NOW!?": {
    "file": "data/clips/keikosgonnahaveababy.mp4",
    "description": "Quark Worf DS9. Deep Space Nine.",
    "url": "https://i.imgur.com/a3bRlus.mp4"
  },
  "Kevin - All Husnock Everywhere!": {
    "file": "data/clips/kevinallhusnockeverywhere.mp4",
    "description": "Kevin Uxbridge killed them all, all husnock everywhere",
    "url": "https://i.imgur.com/ABiJChK.mp4"
  },
  "Mariner - Hey That's An Anus!": {
    "file": "data/clips/marinerthatsananus.mp4",
    "description": "Mariner That's An Anus Naked Time",
    "url": "https://i.imgur.com/Cyael6e.mp4"
  },
  "MOOPSY!": {
    "file": "data/clips/moopsy.mp4",
    "description": "Lower Decks",
    "url": "https://i.imgur.com/cAOsREr.mp4"
  },
  "O'Brien - He Was A Union Man!": {
    "file": "data/clips/hewasanunionman.mp4",
    "description": "Obrien He Was More Than A Hero, He Was a Union Man! Deep Space Nine. DS9.",
    "url": "https://i.imgur.com/NRe1yrs.mp4"
  },
  "Picard - Damn You!": {
    "file": "data/clips/picarddamnyou.mp4",
    "description": "Picard Damn You",
    "url": "https://i.imgur.com/vuDmv7F.mp4"
  },
  "Picard - Get Off My Bridge": {
    "file": "data/clips/picardgetoffmybridge.mp4",
    "description": "Picard get off my bridge",
    "url": "https://i.imgur.com/ZABuj44.mp4"
  },
  "Picard - Engage!": {
    "file": "data/clips/picardengage.mp4",
    "description": "Picard Engage",
    "url": "https://i.imgur.com/h5qBsKj.mp4"
  },
  "Picard - Nooo!": {
    "file": "data/clips/picardnooo.mp4",
    "description": "Picard No Nooo First Contact",
    "url": "https://i.imgur.com/Y97oUGP.mp4"
  },
  "Picard - Thirties...": {
    "file": "data/clips/picardthirties.mp4",
    "description": "Sub Rosa. TNG. The Next Generation.",
    "url": "https://i.imgur.com/oki31YA.mp4"
  },
  "Picard - We Have No Law To Fit Your Crime!": {
    "file": "data/clips/picardwehavenolawtofityourcrime.mp4",
    "description": "Picard we have no law to fit your crime",
    "url": "https://i.imgur.com/l9v4dnD.mp4"
  },
  "Picard Laughing (Hurr Hurr)": {
    "file": "data/clips/picardlaughinghurrhurr.mp4",
    "description": "Picard Laugh Laughing hurr hurr",
    "url": "https://i.imgur.com/BzeN4li.mp4"
  },
  "Picard Laughing (Smiley Face)": {
    "file": "data/clips/picardlaughingsmileyface.mp4",
    "description": "Picard Laugh Laughing Smiley Face Vapor",
    "url": "https://i.imgur.com/VpK35NR.mp4"
  },
  "Picard - Make It So!": {
    "file": "data/clips/picardmakeitso.mp4",
    "description": "Picard Make It So",
    "url": "https://i.imgur.com/95pzmOq.mp4"
  },
  "Picard With A Machine Gun": {
    "file": "data/clips/picardmachinegun.mp4",
    "description": "Picard With A Machine Tommy Gun",
    "url": "https://i.imgur.com/lBBMwBG.mp4"
  },
  "Suzy Q and Q (Reproduction) - Janeway: That Was It!?": {
    "file": "data/clips/suzyqandqthatwasit.mp4",
    "description": "Voyager. VOY.",
    "url": "https://i.imgur.com/7HwTaBQ.mp4"
  },
  "Quark's Is Fun": {
    "file": "data/clips/quarksisfun.mp4",
    "description": "Come to Quark's, Quark's is fun, come right now, don't walk, run! Oh I love the part where my name rotates around.",
    "url": "https://i.imgur.com/vKBlfXo.mp4"
  },
  "Ransom In The Mariner Ball-Kicking Machine": {
    "file": "data/clips/ransomballkickingmachine.mp4",
    "description": "Mariner Ransom Ball Kicking",
    "url": "https://i.imgur.com/qjYcJuy.mp4"
  },
  "Riker - Anybody Canyon": {
    "file": "data/clips/rikeranybodycanyon.mp4",
    "description": "Riker - Anybody Canyon",
    "url": "https://i.imgur.com/850Z3MX.mp4"
  },
  "Shaka When The Walls Fell": {
    "file": "data/clips/shakawhenthewallsfell.mp4",
    "description": "Tamarian Language Shaka When The Walls Fell",
    "url": "https://i.imgur.com/XzXRAfj.mp4"
  },
  "She Who Is My Wife": {
    "file": "data/clips/shewhosimywife.mp4",
    "description": "Sarek TNG The Next Generation",
    "url": "https://i.imgur.com/gDlMu4n.mp4"
  },
  "Sokath His Eyes Uncovered": {
    "file": "data/clips/sokathhiseyesuncovered.mp4",
    "description": "Tamarian Language Sokath His Eyes Uncovered",
    "url": "https://i.imgur.com/oBIhXlB.mp4"
  },
  "Spock - Hijinks Are The Most Logical Course Of Action": {
    "file": "data/clips/hijinksarethemostlogicalcourseofaction.mp4",
    "description": "I do not like Hijinks, in that we are in agreement but it appears hijinks are the most logical course of action.",
    "url": "https://i.imgur.com/uzd1lRo.mp4"
  },
  "Spock (TAS) - I Just Realized That": {
    "file": "data/clips/spockijustrealizedthat.mp4",
    "description": "TAS. The Animated Series.",
    "url": "https://i.imgur.com/QTj2Rml.mp4"
  },
  "Spock - This Is Coming Dangerously Close to Hijinks": {
    "file": "data/clips/dangerouslyclosetohijinks.mp4",
    "description": "This is coming dangerously close to hijinks, who doesn't love hijinks?",
    "url": "https://i.imgur.com/taSBgo5.mp4"
  },
  "Thug Life Pulaski": {
    "file": "data/clips/thuglifepulaski.mp4",
    "description": "Gangster. Gangsta. Meme. TNG. The NExt Generation.",
    "url": "https://i.imgur.com/lFMC60F.mp4"
  },
  "Tom Paris - It's THE VOYAGER!": {
    "file": "data/clips/tomparisitsthevoyager.mp4",
    "description": "Tom Paris - It's The Voyager",
    "url": "https://i.imgur.com/bU4KAxw.mp4"
  },
  "Tough Little Ship... Little!?": {
    "file": "data/clips/toughlittleshiplittle.mp4",
    "description": "Riker. Worf. First Contact.",
    "url": "https://i.imgur.com/i4zDyoq.mp4"
  },
  "Tuvok - We Have Lost Our Sex Appeal": {
    "file": "data/clips/tuvokwehavelostoursexappeal.mp4",
    "description": "Tuvok - We Have Lost Our Sex Appeal Captain",
    "url": "https://i.imgur.com/aHQg5qh.mp4"
  },
  "Weyoun - How Delightful!": {
    "file": "data/clips/weyounhowdelightful.mp4",
    "description": "Weyoun how delightful",
    "url": "https://i.imgur.com/ysSanNI.mp4"
  },
  "Wesley - About This Long, This Thick?": {
    "file": "data/clips/wesleythislongthisthick.mp4",
    "description": "Edo. Knuck. Dong.",
    "url": "https://i.imgur.com/ZVFzw7j.mp4"
  },
  "Worf - It's Not Funny, But I Get It.": {
    "file": "data/clips/worftnotfunnybutigetit.mp4",
    "description": "Jadzia. DS9. Deep Space Nine.",
    "url": "https://i.imgur.com/OdpQ17D.mp4"
  },
  "Worf - That Is A Joke! I Get It!": {
    "file": "data/clips/worfthatisajoke.mp4",
    "description": "Jadzia. DS9. Deep Space Nine.",
    "url": "https://i.imgur.com/OdpQ17D.mp4"
  },
  "Worf - A Warrior's Drink!": {
    "file": "data/clips/worfwarriorsdrink.mp4",
    "description": "Worf Warriors Drink Prune Juice",
    "url": "https://i.imgur.com/TPgzycP.mp4"
  },
  "Worf - Delicious": {
    "file": "data/clips/worfdelicious.mp4",
    "description": "Worf - Delicious",
    "url": "https://i.imgur.com/vZ1BtgX.mp4"
  },
  "Worf - Good Tea, Nice House": {
    "file": "data/clips/worfgoodteanicehouse.mp4",
    "description": "Worf - Good Tea Nice House",
    "url": "https://i.imgur.com/VqHmdIx.mp4"
  },
  "Worf - I Admire Gall": {
    "file": "data/clips/worfiadmiregall.mp4",
    "description": "Worf - I Admire Gall",
    "url": "https://i.imgur.com/hpFlcki.mp4"
  },
  "Zephram Cochrane - Some Kind Of Star Trek": {
    "file": "data/clips/somekindofstartrek.mp4",
    "description": "Star Trek: First Contact",
    "url": "https://i.imgur.com/p3JUi9I.mp4"
  }
}